_pyfastmask.cpython-39-x86_64-linux-gnu.so
pyfastmask/__init__.py
pyfastmask-1.2.0.dist-info/RECORD
pyfastmask-1.2.0.dist-info/WHEEL
pyfastmask-1.2.0.dist-info/LICENSE
pyfastmask-1.2.0.dist-info/top_level.txt
pyfastmask-1.2.0.dist-info/METADATA
