Metadata-Version: 2.1
Name: pyfastmask
Version: 1.2.0
Summary: Fast low color mask read/write
Author: Andrei Luzan
License: MIT License
Project-URL: Repository, https://github.com/JIy3AHKO/pyfastmask
Project-URL: Issues, https://github.com/JIy3AHKO/pyfastmask/issues
Keywords: mask,segmentation,fast,read,write
Classifier: Intended Audience :: Developers
Classifier: Intended Audience :: Science/Research
Classifier: License :: OSI Approved :: MIT License
Classifier: Programming Language :: Python :: 3
Classifier: Programming Language :: C++
Classifier: Operating System :: OS Independent
Classifier: Topic :: Software Development :: Libraries :: Python Modules
Classifier: Topic :: Multimedia :: Graphics
License-File: LICENSE
Requires-Dist: numpy>=1.20.0
